{"v":3,"stories":{"example-curtain--docs":{"id":"example-curtain--docs","title":"Example/Curtain","name":"Docs","importPath":"./src/components/Curtain/Curtain.stories.ts","tags":["autodocs","docs"],"storiesImports":[],"kind":"Example/Curtain","story":"Docs","parameters":{"__id":"example-curtain--docs","docsOnly":true,"fileName":"./src/components/Curtain/Curtain.stories.ts"}},"example-curtain--primary":{"id":"example-curtain--primary","name":"Primary","title":"Example/Curtain","importPath":"./src/components/Curtain/Curtain.stories.ts","tags":["autodocs","story"],"kind":"Example/Curtain","story":"Primary","parameters":{"__id":"example-curtain--primary","docsOnly":false,"fileName":"./src/components/Curtain/Curtain.stories.ts"}},"example-curtain--with-curtain-children":{"id":"example-curtain--with-curtain-children","name":"With Curtain Children","title":"Example/Curtain","importPath":"./src/components/Curtain/Curtain.stories.ts","tags":["autodocs","story"],"kind":"Example/Curtain","story":"With Curtain Children","parameters":{"__id":"example-curtain--with-curtain-children","docsOnly":false,"fileName":"./src/components/Curtain/Curtain.stories.ts"}}}}
